fyers_api_helper/__init__.py
fyers_api_helper/access.py
fyers_api_helper/cli.py
fyers_api_helper/config.py
fyers_api_helper/data_manipulation.py
fyers_api_helper/search.py
fyers_api_helper/static/css/access_global.css
fyers_api_helper/static/css/access_index.css
fyers_api_helper/static/css/config_global.css
fyers_api_helper/static/css/config_index.css
fyers_api_helper/static/images/config_logo.svg
fyers_api_helper/templates/access.html
fyers_api_helper/templates/config.html
fyers_api_helper-0.7.2.dist-info/LICENSE
fyers_api_helper-0.7.2.dist-info/METADATA
fyers_api_helper-0.7.2.dist-info/WHEEL
fyers_api_helper-0.7.2.dist-info/entry_points.txt
fyers_api_helper-0.7.2.dist-info/RECORD
